<?xml version="1.0" encoding="UTF-8"?>
<data xmlns="http://www.woltlab.com" xmlns:xsi="http://www.w3.org/2001/XMLSchema-instance" xsi:schemaLocation="http://www.woltlab.com http://www.woltlab.com/XSD/maelstrom/eventListener.xsd">
	<import>
		<!-- show hint -->
		<eventlistener>
			<eventclassname>wcf\page\AbstractPage</eventclassname>
			<eventname>assignVariables</eventname>
			<listenerclassname>wcf\system\event\listener\ToDoWarningListener</listenerclassname>
			<environment>user</environment>
			<inherit>1</inherit>
		</eventlistener>
		
		<!-- renaming users -->
		<eventlistener>
			<eventclassname>wcf\data\user\UserAction</eventclassname>
			<eventname>rename</eventname>
			<listenerclassname>wcf\system\event\listener\ToDoUserActionRenameListener</listenerclassname>
			<environment>user</environment>
		</eventlistener>
		<eventlistener>
			<eventclassname>wcf\data\user\UserAction</eventclassname>
			<eventname>rename</eventname>
			<listenerclassname>wcf\system\event\listener\ToDoUserActionRenameListener</listenerclassname>
			<environment>admin</environment>
		</eventlistener>
	</import>
</data>